README.md
setup.py
qipype/__init__.py
qipype/base.py
qipype/commands.py
qipype/fitting.py
qipype/fsl.py
qipype/parmesan.py
qipype/sims.py
qipype/utils.py
qipype.egg-info/PKG-INFO
qipype.egg-info/SOURCES.txt
qipype.egg-info/dependency_links.txt
qipype.egg-info/requires.txt
qipype.egg-info/top_level.txt
qipype/workflows/__init__.py
qipype/workflows/cest.py
qipype/workflows/mpm.py
qipype/workflows/prep.py