Metadata-Version: 2.1
Name: qipype
Version: 3.2
Summary: nipype interfaces to QUantitative Imaging Tools
Home-page: https://github.com/spinicist/quit
Author: Tobias Wood
Author-email: tobias@spinicist.org.uk
License: MPL
Keywords: neuroimaging mri
Platform: UNKNOWN
Classifier: Topic :: Scientific/Engineering :: Physics
Classifier: Programming Language :: Python :: 3
Requires-Python: >=3
